django_amber
