Metadata-Version: 1.0
Name: django-amber
Version: 0.6.0
Summary: A Django-powered static site generator
Home-page: http://github.com/inglesp/django-amber
Author: Peter Inglesby
Author-email: peter.inglesby@gmail.com
License: License :: OSI Approved :: MIT License
Platform: UNKNOWN
